{"version": "1.1.0",
 "packagesDir": ".lake/packages",
 "packages":
 [{"url": "https://github.com/nathanial/chronicle",
   "type": "git",
   "subDir": null,
   "scope": "",
   "rev": "475d49af34c167598fe25e554f9bf8db96237a6b",
   "name": "chronicle",
   "manifestFile": "lake-manifest.json",
   "inputRev": "v0.0.2",
   "inherited": false,
   "configFile": "lakefile.lean"},
  {"url": "https://github.com/nathanial/reactive",
   "type": "git",
   "subDir": null,
   "scope": "",
   "rev": "85e85963311ae1d4ddeb619018382a5995b074db",
   "name": "reactive",
   "manifestFile": "lake-manifest.json",
   "inputRev": "v0.1.3",
   "inherited": false,
   "configFile": "lakefile.lean"},
  {"url": "https://github.com/nathanial/raster",
   "type": "git",
   "subDir": null,
   "scope": "",
   "rev": "578c2a224908b16068d3b959487e2d73adae7e8c",
   "name": "raster",
   "manifestFile": "lake-manifest.json",
   "inputRev": "v0.0.3",
   "inherited": false,
   "configFile": "lakefile.lean"},
  {"url": "https://github.com/nathanial/crucible",
   "type": "git",
   "subDir": null,
   "scope": "",
   "rev": "6fcf6d3ab5fbfb4857db2f65111beb319ad5bd2e",
   "name": "crucible",
   "manifestFile": "lake-manifest.json",
   "inputRev": "v0.0.7",
   "inherited": false,
   "configFile": "lakefile.lean"},
  {"url": "https://github.com/nathanial/chronos-lean",
   "type": "git",
   "subDir": null,
   "scope": "",
   "rev": "a7297424e041fbc7c6f8655bd0fb955cca2fba2a",
   "name": "chronos",
   "manifestFile": "lake-manifest.json",
   "inputRev": "v0.0.2",
   "inherited": true,
   "configFile": "lakefile.lean"},
  {"url": "https://github.com/leanprover-community/plausible.git",
   "type": "git",
   "subDir": null,
   "scope": "",
   "rev": "160af9e8e7d4ae448f3c92edcc5b6a8522453f11",
   "name": "plausible",
   "manifestFile": "lake-manifest.json",
   "inputRev": "v4.26.0",
   "inherited": true,
   "configFile": "lakefile.toml"},
  {"url": "https://github.com/nathanial/staple",
   "type": "git",
   "subDir": null,
   "scope": "",
   "rev": "1040b375bdd19a6e94374b6e97041cf61f9d307f",
   "name": "staple",
   "manifestFile": "lake-manifest.json",
   "inputRev": "v0.0.2",
   "inherited": true,
   "configFile": "lakefile.lean"}],
 "name": "terminus",
 "lakeDir": ".lake"}
